nuVeto/__init__.py
nuVeto/mu.py
nuVeto/nuveto.py
nuVeto/uncertainties.py
nuVeto/utils.py
nuVeto/data/corsika/eff_maxmu.npz
nuVeto/data/corsika/eff_summu.npz
nuVeto/data/corsika/num_maxmu.npz
nuVeto/data/corsika/num_summu.npz
nuVeto/data/decay_distributions/D+_numu.npz
nuVeto/data/decay_distributions/D0_numu.npz
nuVeto/data/decay_distributions/Ds_numu.npz
nuVeto/data/decay_distributions/K+_numu.npz
nuVeto/data/decay_distributions/K0L_numu.npz
nuVeto/data/mmc/ice_allm97.npz
nuVeto/data/mmc/ice_bb.npz
nuVeto/data/mmc/water_allm97.npz
nuVeto/data/mmc/water_bb.npz
nuVeto/data/prpl/ice_allm97_sigmoid_0.75_0.1.npz
nuVeto/data/prpl/ice_allm97_sigmoid_0.75_0.25.npz
nuVeto/data/prpl/ice_allm97_step_0.75.npz
nuVeto/data/prpl/ice_allm97_step_1.npz
nuVeto/data/prpl/ice_bb_step_1.npz
nuVeto/data/prpl/water_allm97_step_1.npz
nuVeto/data/prpl/water_bb_step_1.npz
nuVeto/examples/__init__.py
nuVeto/examples/plots.py
nuVeto/external/__init__.py
nuVeto/external/helper.py
nuVeto/external/selfveto.py
nuVeto/tests/test_app.py
nuveto-2.7.0.dist-info/licenses/LICENSE
nuveto-2.7.0.dist-info/METADATA
nuveto-2.7.0.dist-info/WHEEL
nuveto-2.7.0.dist-info/top_level.txt
nuveto-2.7.0.dist-info/RECORD
