Metadata-Version: 2.4
Name: nuVeto
Version: 2.7.0
Summary: Package implements the formalism for calculating passing fraction as discussed in JCAP07(2018)047.
Maintainer-email: Tianlu Yuan <tyuan@icecube.wisc.edu>
License: GNU LESSER GENERAL PUBLIC LICENSE
Project-URL: Repository, https://github.com/tianluyuan/nuVeto.git
Classifier: Intended Audience :: Science/Research
Classifier: License :: OSI Approved :: GNU Lesser General Public License v3 or later (LGPLv3+)
Classifier: Natural Language :: English
Classifier: Programming Language :: Python :: 3
Classifier: Topic :: Scientific/Engineering
Requires-Python: >=3.9
License-File: LICENSE
Requires-Dist: numpy<2.4.0,>=1.7.0
Requires-Dist: scipy<2,>=1.6.0
Requires-Dist: MCEq<2,>=1.3.0
Requires-Dist: pandas<3
Provides-Extra: plotting
Requires-Dist: matplotlib; extra == "plotting"
Provides-Extra: pythia8
Requires-Dist: pythia8mc; extra == "pythia8"
Requires-Dist: matplotlib; extra == "pythia8"
Provides-Extra: testing
Requires-Dist: pytest; extra == "testing"
Dynamic: license-file
